Metadata-Version: 2.1
Name: motorcortex-mobile-control-python
Version: 0.2.0
Summary: Python bindings for Motorcortex Mobile Platform Control
Home-page: https://www.motorcortex.io
Author: Alexey Zakharov
Author-email: info@vectioneer.com
License: MIT
Platform: UNKNOWN
